{
  "api": {
    "dogsApi": {
      "dependsOn": [
        {
          "attributes": [
            "Name",
            "Arn"
          ],
          "category": "function",
          "resourceName": "dogsFunction"
        }
      ],
      "providerPlugin": "awscloudformation",
      "service": "API Gateway"
    },
    "usersApi": {
      "dependsOn": [
        {
          "attributes": [
            "Name",
            "Arn"
          ],
          "category": "function",
          "resourceName": "usersFunction"
        }
      ],
      "providerPlugin": "awscloudformation",
      "service": "API Gateway"
    }
  },
  "auth": {
    "waqqlya798f58a": {
      "customAuth": false,
      "dependsOn": [],
      "frontendAuthConfig": {
        "mfaConfiguration": "OFF",
        "mfaTypes": [
          "SMS"
        ],
        "passwordProtectionSettings": {
          "passwordPolicyCharacters": [],
          "passwordPolicyMinLength": 8
        },
        "signupAttributes": [
          "EMAIL"
        ],
        "socialProviders": [],
        "usernameAttributes": [
          "EMAIL"
        ],
        "verificationMechanisms": [
          "EMAIL"
        ]
      },
      "providerPlugin": "awscloudformation",
      "service": "Cognito"
    }
  },
  "function": {
    "dogsFunction": {
      "build": true,
      "dependsOn": [
        {
          "attributeEnvMap": {
            "Arn": "TABLE_ARN",
            "Name": "TABLE_NAME"
          },
          "attributes": [
            "Name",
            "Arn"
          ],
          "category": "storage",
          "resourceName": "dogsTable"
        }
      ],
      "providerPlugin": "awscloudformation",
      "service": "Lambda"
    },
    "usersFunction": {
      "build": true,
      "dependsOn": [
        {
          "attributeEnvMap": {
            "Arn": "TABLE_ARN",
            "Name": "TABLE_NAME"
          },
          "attributes": [
            "Name",
            "Arn"
          ],
          "category": "storage",
          "resourceName": "usersTable"
        }
      ],
      "providerPlugin": "awscloudformation",
      "service": "Lambda"
    }
  },
  "hosting": {
    "amplifyhosting": {
      "providerPlugin": "awscloudformation",
      "service": "amplifyhosting",
      "type": "manual"
    }
  },
  "parameters": {
    "AMPLIFY_function_usersFunction_deploymentBucketName": {
      "usedBy": [
        {
          "category": "function",
          "resourceName": "usersFunction"
        }
      ]
    },
    "AMPLIFY_function_usersFunction_s3Key": {
      "usedBy": [
        {
          "category": "function",
          "resourceName": "usersFunction"
        }
      ]
    },
    "AMPLIFY_hosting_amplifyhosting_appId": {
      "usedBy": [
        {
          "category": "hosting",
          "resourceName": "amplifyhosting"
        }
      ]
    },
    "AMPLIFY_hosting_amplifyhosting_type": {
      "usedBy": [
        {
          "category": "hosting",
          "resourceName": "amplifyhosting"
        }
      ]
    }
  },
  "storage": {
    "dogsTable": {
      "providerPlugin": "awscloudformation",
      "service": "DynamoDB"
    },
    "usersTable": {
      "providerPlugin": "awscloudformation",
      "service": "DynamoDB"
    }
  }
}